strelok/__init__.py
strelok/feat.py
strelok-0.0.6.dist-info/METADATA
strelok-0.0.6.dist-info/WHEEL
strelok-0.0.6.dist-info/top_level.txt
strelok-0.0.6.dist-info/RECORD
