Metadata-Version: 2.1
Name: strelok
Version: 0.0.6
Summary: Strelok is a simple Python package that provides FEAT, a feature engineering automation toolkit. With a focus on simplicity, it offers user definable pipelines to streamline the feature engineering process and improve the performance of machine learning models
Author: Julius Riel
Author-email: julius.riel@icloud.com
License: UNKNOWN
Keywords: strelok,feature,selection,machine learning
Platform: UNKNOWN
Classifier: Programming Language :: Python :: 3
Classifier: License :: OSI Approved :: MIT License
Classifier: Operating System :: OS Independent
Requires-Python: >=3.6
Requires-Dist: numpy
Requires-Dist: pandas
Requires-Dist: sklearn
Requires-Dist: scipy
